{
    "homepage": "https://sikiapp.net/",
    "version": "0.38.7",
    "url": "https://sikiapp.net/archives/0.38.7/Siki-win32-x64-0.38.7.zip",
    "hash": "01a39bbb411e924c4f0b40833afc54ee1d8c5ffb6cf2a169ba043a06c21a2ad5",
    "license": "",
    "shortcuts": [
        [
            "Siki.exe",
            "Siki"
        ]
    ],
    "extract_dir": "Siki-win32-x64",
    "persist": [
        "data",
        "components"
    ],
    "checkver": {
        "url": "https://sikiapp.net/",
        "re": "Siki-win32-x64-([\\d.-]+).zip"
    },
    "autoupdate": {
        "url": "https://sikiapp.net/archives/$version/Siki-win32-x64-$version.zip"
    }
}
